mcstructure/__init__.py
mcstructure/py.typed
mcstructure-0.0.1b6.dist-info/licenses/LICENSE.txt
mcstructure-0.0.1b6.dist-info/METADATA
mcstructure-0.0.1b6.dist-info/WHEEL
mcstructure-0.0.1b6.dist-info/top_level.txt
mcstructure-0.0.1b6.dist-info/RECORD
