Metadata-Version: 2.4
Name: mcstructure
Version: 0.0.1b6
Summary: Read and write Minecraft .mcstructure files.
License: MIT
Project-URL: Documentation, https://mcstructure.readthedocs.io/en/latest/
Project-URL: Source Code, https://github.com/phoenixr-codes/mcstructure/
Keywords: mcstructure,Minecraft
Classifier: Development Status :: 4 - Beta
Classifier: Intended Audience :: Developers
Classifier: Intended Audience :: Education
Classifier: License :: OSI Approved :: MIT License
Classifier: Natural Language :: English
Classifier: Programming Language :: Python :: 3
Classifier: Topic :: Games/Entertainment
Classifier: Typing :: Typed
Requires-Python: >=3.11
License-File: LICENSE.txt
Requires-Dist: numpy==2.3.0
Requires-Dist: pynbt==2
Provides-Extra: dev
Requires-Dist: pytest>=8; extra == "dev"
Requires-Dist: mypy==1.16.1; extra == "dev"
Requires-Dist: black==25.1.0; extra == "dev"
Provides-Extra: docs
Requires-Dist: furo; extra == "docs"
Requires-Dist: myst-parser>=2; extra == "docs"
Requires-Dist: Sphinx>=7; extra == "docs"
Requires-Dist: sphinx-copybutton>=0; extra == "docs"
Dynamic: license-file
